odoo/addons/l10n_it_edi_doi_extension/README.rst
odoo/addons/l10n_it_edi_doi_extension/__init__.py
odoo/addons/l10n_it_edi_doi_extension/__manifest__.py
odoo/addons/l10n_it_edi_doi_extension/i18n/it.po
odoo/addons/l10n_it_edi_doi_extension/i18n/l10n_it_edi_doi_extension.pot
odoo/addons/l10n_it_edi_doi_extension/models/__init__.py
odoo/addons/l10n_it_edi_doi_extension/models/account_move.py
odoo/addons/l10n_it_edi_doi_extension/models/account_tax.py
odoo/addons/l10n_it_edi_doi_extension/models/declaration_of_intent.py
odoo/addons/l10n_it_edi_doi_extension/models/purchase_order.py
odoo/addons/l10n_it_edi_doi_extension/models/res_company.py
odoo/addons/l10n_it_edi_doi_extension/readme/CONTRIBUTORS.md
odoo/addons/l10n_it_edi_doi_extension/readme/DESCRIPTION.md
odoo/addons/l10n_it_edi_doi_extension/readme/USAGE.md
odoo/addons/l10n_it_edi_doi_extension/static/description/icon.png
odoo/addons/l10n_it_edi_doi_extension/static/description/index.html
odoo/addons/l10n_it_edi_doi_extension/tests/__init__.py
odoo/addons/l10n_it_edi_doi_extension/tests/test_doi_issued_from_company.py
odoo/addons/l10n_it_edi_doi_extension/views/account_move_views.xml
odoo/addons/l10n_it_edi_doi_extension/views/l10n_it_edi_doi_declaration_of_intent_views.xml
odoo/addons/l10n_it_edi_doi_extension/views/purchase_order_views.xml
odoo/addons/l10n_it_edi_doi_extension/views/res_company.xml
odoo_addon_l10n_it_edi_doi_extension-18.0.1.0.0.4.dist-info/METADATA
odoo_addon_l10n_it_edi_doi_extension-18.0.1.0.0.4.dist-info/WHEEL
odoo_addon_l10n_it_edi_doi_extension-18.0.1.0.0.4.dist-info/top_level.txt
odoo_addon_l10n_it_edi_doi_extension-18.0.1.0.0.4.dist-info/RECORD
